{"type":"FeatureCollection","features":[{"type":"Feature","geometry":{"type":"Point","coordinates":[107.4891108,-6.8365412]},"properties":{"id":3468494610,"bus":"yes","highway":"bus_stop","name":"Cihaliwung, Padalarang","public_transport":"platform","ref":"Cihaliwung, Padalarang"}},{"type":"Feature","geometry":{"type":"Point","coordinates":[107.497183,-6.8432738]},"properties":{"id":3468494612,"bus":"yes","highway":"bus_stop","name":"Stasiun KAI Padalarang","public_transport":"platform","ref":"Stasiun Padalarang"}},{"type":"Feature","geometry":{"type":"Point","coordinates":[107.4849802,-6.842545]},"properties":{"id":3889788940,"bus":"yes","highway":"bus_stop","name":"Simpang Pasar Tagog","public_transport":"platform"}}]}