{"type":"FeatureCollection","features":[{"type":"Feature","geometry":{"type":"Point","coordinates":[107.9769427,-7.0377722]},"properties":{"id":3890313812,"bus":"yes","highway":"bus_stop","name":"Limbangan/Cijolang","public_transport":"platform"}},{"type":"Feature","geometry":{"type":"Point","coordinates":[107.8853248,-7.0187098]},"properties":{"id":3890313813,"bus":"yes","name":"Nagreg","public_transport":"platform","ref":"Nagreg"}}]}