{"type":"FeatureCollection","features":[{"type":"Feature","geometry":{"type":"Point","coordinates":[107.5720023,-6.9155783]},"properties":{"id":11711275768,"bus":"yes","highway":"bus_stop","name":"Optik Krida","public_transport":"platform","route_ref":"2"}}]}