{"type":"FeatureCollection","features":[{"type":"Feature","geometry":{"type":"Point","coordinates":[107.6065579,-6.9187567]},"properties":{"id":29354882,"bus":"yes","highway":"bus_stop","name":"Banceuy","public_transport":"platform","ref":"Banceuy/ABC","route_ref":"3"}},{"type":"Feature","geometry":{"type":"Point","coordinates":[107.6064724,-6.9205635]},"properties":{"id":10778288303,"bus":"yes","highway":"bus_stop","name":"Banceuy","public_transport":"platform","shelter":"yes","source":"POI_WRI_Survey_2023"}},{"type":"Feature","geometry":{"type":"Point","coordinates":[107.6062023,-6.923845]},"properties":{"id":11871900165,"bus":"yes","highway":"bus_stop","name":"Grand Yogya Kepatihan","public_transport":"platform","route_ref":"3"}},{"type":"Feature","geometry":{"type":"Point","coordinates":[107.579147,-6.9081391]},"properties":{"id":11878347327,"bus":"yes","highway":"bus_stop","name":"Andir","public_transport":"platform"}}]}